{
  "resourceType": "PractitionerRole",
  "id": "diagnostic-barrett-carey",
  "meta": {
    "profile": [
      "http://hl7.org.au/fhir/core/StructureDefinition/au-core-practitionerrole"
    ]
  },
  "identifier": [
    {
      "type": {
        "coding": [
          {
            "system": "http://terminology.hl7.org.au/CodeSystem/v2-0203",
            "code": "UPIN"
          }
        ],
        "text": "Medicare Provider Number"
      },
      "system": "http://ns.electronichealth.net.au/id/medicare-provider-number",
      "value": "2448851H"
    }
  ],
  "practitioner": {
    "reference": "Practitioner/barrett-carey"
  },
  "organization": {
    "reference": "Organization/frenchs-forest-east-radiology"
  },
  "code": [
    {
      "coding": [
        {
          "system": "http://www.abs.gov.au/ausstats/abs@.nsf/mf/1220.0",
          "code": "253917",
          "display": "Diagnostic and Interventional Radiologist"
        }
      ]
    }
  ],
  "specialty": [
    {
      "coding": [
        {
          "system": "http://snomed.info/sct",
          "code": "408455009",
          "display": "Interventional radiology - speciality"
        }
      ]
    }
  ],
  "location": [
    {
      "reference": "Location/frenchs-forest-east-radiology"
    }
  ],
  "telecom": [
    {
      "system": "phone",
      "value": "0270107743",
      "use": "work"
    },
    {
      "system": "email",
      "value": "carey.barrett@frenchsforesteastrd.example.net",
      "use": "work"
    }
  ]
}